[
  {
    "source": 0,
    "target": 1,
    "my_cost": "inf",
    "nx_cost": "inf",
    "my_time": 0.0,
    "nx_time": 0.0,
    "equal": true
  },
  {
    "source": 0,
    "target": 2,
    "my_cost": 708.0,
    "nx_cost": 708.0,
    "my_time": 0.0009982585906982422,
    "nx_time": 0.0,
    "equal": true
  },
  {
    "source": 0,
    "target": 3,
    "my_cost": 972.0,
    "nx_cost": 972.0,
    "my_time": 0.0010044574737548828,
    "nx_time": 0.0,
    "equal": true
  },
  {
    "source": 0,
    "target": 4,
    "my_cost": 124.0,
    "nx_cost": 124.0,
    "my_time": 0.0010030269622802734,
    "nx_time": 0.0,
    "equal": true
  },
  {
    "source": 0,
    "target": 5,
    "my_cost": 770.0,
    "nx_cost": 770.0,
    "my_time": 0.0010557174682617188,
    "nx_time": 0.0,
    "equal": true
  },
  {
    "source": 0,
    "target": 6,
    "my_cost": 466.0,
    "nx_cost": 466.0,
    "my_time": 0.0010132789611816406,
    "nx_time": 0.0,
    "equal": true
  },
  {
    "source": 0,
    "target": 7,
    "my_cost": -64.0,
    "nx_cost": -64.0,
    "my_time": 0.0,
    "nx_time": 0.0009999275207519531,
    "equal": true
  },
  {
    "source": 0,
    "target": 8,
    "my_cost": -248.0,
    "nx_cost": -248.0,
    "my_time": 0.0,
    "nx_time": 0.0,
    "equal": true
  },
  {
    "source": 0,
    "target": 9,
    "my_cost": 1158.0,
    "nx_cost": 1158.0,
    "my_time": 0.0010039806365966797,
    "nx_time": 0.0,
    "equal": true
  },
  {
    "source": 1,
    "target": 2,
    "my_cost": 858.0,
    "nx_cost": 858.0,
    "my_time": 0.0009961128234863281,
    "nx_time": 0.0,
    "equal": true
  },
  {
    "source": 1,
    "target": 3,
    "my_cost": 1304.0,
    "nx_cost": 1304.0,
    "my_time": 0.0020003318786621094,
    "nx_time": 0.0,
    "equal": true
  },
  {
    "source": 1,
    "target": 4,
    "my_cost": 322.0,
    "nx_cost": 322.0,
    "my_time": 0.0010056495666503906,
    "nx_time": 0.0009953975677490234,
    "equal": true
  },
  {
    "source": 1,
    "target": 5,
    "my_cost": 229.0,
    "nx_cost": 229.0,
    "my_time": 0.0,
    "nx_time": 0.000997781753540039,
    "equal": true
  },
  {
    "source": 1,
    "target": 6,
    "my_cost": 766.0,
    "nx_cost": 766.0,
    "my_time": 0.0,
    "nx_time": 0.0,
    "equal": true
  },
  {
    "source": 1,
    "target": 7,
    "my_cost": 453.0,
    "nx_cost": 453.0,
    "my_time": 0.0,
    "nx_time": 0.0,
    "equal": true
  },
  {
    "source": 1,
    "target": 8,
    "my_cost": 269.0,
    "nx_cost": 269.0,
    "my_time": 0.02393817901611328,
    "nx_time": 0.0,
    "equal": true
  },
  {
    "source": 1,
    "target": 9,
    "my_cost": 242.0,
    "nx_cost": 242.0,
    "my_time": 0.0009968280792236328,
    "nx_time": 0.0,
    "equal": true
  },
  {
    "source": 2,
    "target": 3,
    "my_cost": 2263.0,
    "nx_cost": 2263.0,
    "my_time": 0.0010023117065429688,
    "nx_time": 0.0,
    "equal": true
  },
  {
    "source": 2,
    "target": 4,
    "my_cost": 1415.0,
    "nx_cost": 1415.0,
    "my_time": 0.0010023117065429688,
    "nx_time": 0.0,
    "equal": true
  },
  {
    "source": 2,
    "target": 5,
    "my_cost": 2061.0,
    "nx_cost": 2061.0,
    "my_time": 0.000997304916381836,
    "nx_time": 0.0,
    "equal": true
  },
  {
    "source": 2,
    "target": 6,
    "my_cost": 974.0,
    "nx_cost": 974.0,
    "my_time": 0.0009992122650146484,
    "nx_time": 0.0,
    "equal": true
  },
  {
    "source": 2,
    "target": 7,
    "my_cost": 1227.0,
    "nx_cost": 1227.0,
    "my_time": 0.0010001659393310547,
    "nx_time": 0.0,
    "equal": true
  },
  {
    "source": 2,
    "target": 8,
    "my_cost": 1043.0,
    "nx_cost": 1043.0,
    "my_time": 0.0010273456573486328,
    "nx_time": 0.0,
    "equal": true
  },
  {
    "source": 2,
    "target": 9,
    "my_cost": 450.0,
    "nx_cost": 450.0,
    "my_time": 0.0020346641540527344,
    "nx_time": 0.0,
    "equal": true
  },
  {
    "source": 3,
    "target": 4,
    "my_cost": 922.0,
    "nx_cost": 922.0,
    "my_time": 0.0009961128234863281,
    "nx_time": 0.0,
    "equal": true
  },
  {
    "source": 3,
    "target": 5,
    "my_cost": 2506.0,
    "nx_cost": 2506.0,
    "my_time": 0.0009999275207519531,
    "nx_time": 0.0010006427764892578,
    "equal": true
  },
  {
    "source": 3,
    "target": 6,
    "my_cost": 1954.0,
    "nx_cost": 1954.0,
    "my_time": 0.0009982585906982422,
    "nx_time": 0.0,
    "equal": true
  },
  {
    "source": 3,
    "target": 7,
    "my_cost": 1672.0,
    "nx_cost": 1672.0,
    "my_time": 0.0,
    "nx_time": 0.0010001659393310547,
    "equal": true
  },
  {
    "source": 3,
    "target": 8,
    "my_cost": 1488.0,
    "nx_cost": 1488.0,
    "my_time": 0.0,
    "nx_time": 0.0,
    "equal": true
  },
  {
    "source": 3,
    "target": 9,
    "my_cost": 1430.0,
    "nx_cost": 1430.0,
    "my_time": 0.0015134811401367188,
    "nx_time": 0.0,
    "equal": true
  },
  {
    "source": 4,
    "target": 5,
    "my_cost": 1584.0,
    "nx_cost": 1584.0,
    "my_time": 0.00051116943359375,
    "nx_time": 0.0,
    "equal": true
  },
  {
    "source": 4,
    "target": 6,
    "my_cost": 1280.0,
    "nx_cost": 1280.0,
    "my_time": 0.001012563705444336,
    "nx_time": 0.0005095005035400391,
    "equal": true
  },
  {
    "source": 4,
    "target": 7,
    "my_cost": 750.0,
    "nx_cost": 750.0,
    "my_time": 0.0,
    "nx_time": 0.0,
    "equal": true
  },
  {
    "source": 4,
    "target": 8,
    "my_cost": 566.0,
    "nx_cost": 566.0,
    "my_time": 0.0010132789611816406,
    "nx_time": 0.0007507801055908203,
    "equal": true
  },
  {
    "source": 4,
    "target": 9,
    "my_cost": 1972.0,
    "nx_cost": 1972.0,
    "my_time": 0.0020134449005126953,
    "nx_time": 0.0,
    "equal": true
  },
  {
    "source": 5,
    "target": 6,
    "my_cost": 1373.0,
    "nx_cost": 1373.0,
    "my_time": 0.001001596450805664,
    "nx_time": 0.0010013580322265625,
    "equal": true
  },
  {
    "source": 5,
    "target": 7,
    "my_cost": 843.0,
    "nx_cost": 843.0,
    "my_time": 0.017124414443969727,
    "nx_time": 0.0,
    "equal": true
  },
  {
    "source": 5,
    "target": 8,
    "my_cost": 659.0,
    "nx_cost": 659.0,
    "my_time": 0.0019915103912353516,
    "nx_time": 0.0,
    "equal": true
  },
  {
    "source": 5,
    "target": 9,
    "my_cost": 2065.0,
    "nx_cost": 2065.0,
    "my_time": 0.0010056495666503906,
    "nx_time": 0.0,
    "equal": true
  },
  {
    "source": 6,
    "target": 7,
    "my_cost": 590.0,
    "nx_cost": 590.0,
    "my_time": 0.0,
    "nx_time": 0.0009925365447998047,
    "equal": true
  },
  {
    "source": 6,
    "target": 8,
    "my_cost": 406.0,
    "nx_cost": 406.0,
    "my_time": 0.0,
    "nx_time": 0.0,
    "equal": true
  },
  {
    "source": 6,
    "target": 9,
    "my_cost": 1812.0,
    "nx_cost": 1812.0,
    "my_time": 0.0015118122100830078,
    "nx_time": 0.0,
    "equal": true
  },
  {
    "source": 7,
    "target": 8,
    "my_cost": -184.0,
    "nx_cost": -184.0,
    "my_time": 0.0,
    "nx_time": 0.0,
    "equal": true
  },
  {
    "source": 7,
    "target": 9,
    "my_cost": 1222.0,
    "nx_cost": 1222.0,
    "my_time": 0.0010142326354980469,
    "nx_time": 0.0,
    "equal": true
  },
  {
    "source": 8,
    "target": 9,
    "my_cost": 2526.0,
    "nx_cost": 2526.0,
    "my_time": 0.0005104541778564453,
    "nx_time": 0.0,
    "equal": true
  }
]